polymetro/__init__.py
polymetro/polymetro.py
polymetro-0.0.1.dist-info/LICENSE
polymetro-0.0.1.dist-info/METADATA
polymetro-0.0.1.dist-info/WHEEL
polymetro-0.0.1.dist-info/entry_points.txt
polymetro-0.0.1.dist-info/RECORD
