Metadata-Version: 2.1
Name: polymetro
Version: 0.0.1
Summary: A polyrhythmic metronome with CLI and Jack server connectivity
License: GNU GPL v3
Author: omnitonal.com
Requires-Python: >=3.11,<4.0
Classifier: License :: Other/Proprietary License
Classifier: Programming Language :: Python :: 3
Classifier: Programming Language :: Python :: 3.11
Requires-Dist: JACK-Client (>=0.5.4,<0.6.0)
